{
	"places": [
		{
			"name": "Be Our Guest",
			"link": "https://disneyworld.disney.go.com/login/?returnUrl=/dining/magic-kingdom/be-our-guest-restaurant/availability-modal",

			"reservations": [
				{
					"time": "7:00pm",
					"date": "05/08/21",
					"party":"2"
				},
				{
					"time": "8:00pm",
					"date": "05/08/21",
					"party":"2"
				}
			]
		},
		{
			"name": "Rainforest Cafe",
			"link": "https://disneyworld.disney.go.com/login/?returnUrl=/dining/disney-springs/rainforest-cafe-disney-springs/availability-modal",

			"reservations": [
				{
					"time": "7:00pm",
					"date": "05/08/21",
					"party":"2"
				},
				{
					"time": "8:00pm",
					"date": "05/08/21",
					"party":"2"
				}
			]
		}
    ]
}