{
	"restaurants": [
		{
			"name": "Coral Reef Restaurant",
			"link": "https://disneyworld.disney.go.com/dining/epcot/coral-reef-restaurant/availability-modal",
			"reservations": [
				{
					"date": "08/05/2021",
					"times": ["Lunch", "Dinner"]
				},
				{
					"date": "09/05/2021",
					"times": ["Lunch", "Dinner"]
				},
				{
					"date": "10/05/2021",
					"times": ["Lunch", "Dinner"]
				},
				{
					"date": "11/05/2021",
					"times": ["Lunch", "Dinner"]
				},
				{
					"date": "12/05/2021",
					"times": ["Lunch", "Dinner"]
				},
				{
					"date": "13/05/2021",
					"times": ["Lunch", "Dinner"]
				},
				{
					"date": "14/05/2021",
					"times": ["Lunch", "Dinner"]
				},
				{
					"date": "15/05/2021",
					"times": ["Lunch"]
				}
			]
		},
		{
			"name": "Rainforest Cafe",
			"link": "https://disneyworld.disney.go.com/dining/disney-springs/rainforest-cafe-disney-springs/availability-modal",

			"reservations": [
				{
					"date": "08/05/2021",
					"times": ["Lunch", "Dinner"]
				},
				{
					"date": "09/05/2021",
					"times": ["Lunch", "Dinner"]
				},
				{
					"date": "10/05/2021",
					"times": ["Lunch", "Dinner"]
				},
				{
					"date": "11/05/2021",
					"times": ["Lunch", "Dinner"]
				},
				{
					"date": "12/05/2021",
					"times": ["Lunch", "Dinner"]
				},
				{
					"date": "13/05/2021",
					"times": ["Lunch", "Dinner"]
				},
				{
					"date": "14/05/2021",
					"times": ["Lunch", "Dinner"]
				},
				{
					"date": "15/05/2021",
					"times": ["Lunch"]
				}
			]
		}
    ]
}
